scrython/__init__.py
scrython/base.py
scrython/base_mixins.py
scrython/cache.py
scrython/rate_limiter.py
scrython/types.py
scrython/utils.py
scrython/bulk_data/__init__.py
scrython/bulk_data/bulk_data.py
scrython/bulk_data/bulk_data_mixins.py
scrython/cards/__init__.py
scrython/cards/cards.py
scrython/cards/cards_mixins.py
scrython/catalogs/__init__.py
scrython/catalogs/catalogs.py
scrython/migrations/__init__.py
scrython/migrations/migrations.py
scrython/migrations/migrations_mixins.py
scrython/rulings/__init__.py
scrython/rulings/rulings.py
scrython/rulings/rulings_mixins.py
scrython/sets/__init__.py
scrython/sets/sets.py
scrython/sets/sets_mixins.py
scrython/symbology/__init__.py
scrython/symbology/symbology.py
scrython/symbology/symbology_mixins.py
scrython-2.0.2.dist-info/licenses/LICENSE
scrython-2.0.2.dist-info/METADATA
scrython-2.0.2.dist-info/WHEEL
scrython-2.0.2.dist-info/top_level.txt
scrython-2.0.2.dist-info/RECORD
