Metadata-Version: 2.4
Name: scrython
Version: 2.0.2
Summary: A wrapper for using the Scryfall API.
Author-email: Nanda Scott <nanda1123@gmail.com>
License-Expression: MIT
Project-URL: Homepage, https://github.com/NandaScott/Scrython
Project-URL: Repository, https://github.com/NandaScott/Scrython
Keywords: Scryfall,magic,the gathering,scrython,wrapper
Classifier: Development Status :: 4 - Beta
Classifier: Intended Audience :: Developers
Classifier: Programming Language :: Python :: 3
Classifier: Programming Language :: Python :: 3.10
Classifier: Programming Language :: Python :: 3.11
Classifier: Programming Language :: Python :: 3.12
Classifier: Programming Language :: Python :: 3.13
Requires-Python: >=3.10
License-File: LICENSE
Requires-Dist: typing-extensions>=4.5.0; python_version < "3.11"
Provides-Extra: dev
Requires-Dist: black>=24.0.0; extra == "dev"
Requires-Dist: ruff>=0.1.0; extra == "dev"
Requires-Dist: mypy>=1.8.0; extra == "dev"
Requires-Dist: pytest>=8.0.0; extra == "dev"
Requires-Dist: pytest-cov>=4.1.0; extra == "dev"
Requires-Dist: pre-commit>=3.6.0; extra == "dev"
Provides-Extra: progress
Requires-Dist: tqdm>=4.65.0; extra == "progress"
Dynamic: license-file
